cli/__init__.py
cli/main.py
sapphireui-0.4.4.dist-info/licenses/LICENSE
scripts/generate_markdown.py
scripts/pull_base_ui_components.py
src/__init__.py
src/export.py
src/hooks.py
src/meta.py
src/routes.py
src/src.py
src/comps/docs/wrapper.py
src/comps/ui/buttons.py
src/comps/ui/themes.py
src/comps/ui/titles.py
src/docs/__init__.py
src/docs/constants.py
src/docs/generator.py
src/docs/parser.py
src/docs/style.py
src/docs/library/__init__.py
src/docs/library/base_ui/__init__.py
src/docs/library/base_ui/components/__init__.py
src/docs/library/base_ui/components/base_ui.py
src/docs/library/base_ui/components/component.py
src/docs/library/base_ui/components/base/__init__.py
src/docs/library/base_ui/components/base/accordion.py
src/docs/library/base_ui/components/base/avatar.py
src/docs/library/base_ui/components/base/badge.py
src/docs/library/base_ui/components/base/breadcrumb.py
src/docs/library/base_ui/components/base/button.py
src/docs/library/base_ui/components/base/checkbox.py
src/docs/library/base_ui/components/base/collapsible.py
src/docs/library/base_ui/components/base/context_menu.py
src/docs/library/base_ui/components/base/dialog.py
src/docs/library/base_ui/components/base/input.py
src/docs/library/base_ui/components/base/input_group.py
src/docs/library/base_ui/components/base/kbd.py
src/docs/library/base_ui/components/base/link.py
src/docs/library/base_ui/components/base/menu.py
src/docs/library/base_ui/components/base/popover.py
src/docs/library/base_ui/components/base/scroll_area.py
src/docs/library/base_ui/components/base/select.py
src/docs/library/base_ui/components/base/skeleton.py
src/docs/library/base_ui/components/base/tabs.py
src/docs/library/base_ui/components/base/textarea.py
src/docs/library/base_ui/components/base/theme_switcher.py
src/docs/library/base_ui/components/base/toggle.py
src/docs/library/base_ui/components/base/toggle_group.py
src/docs/library/base_ui/components/base/tooltip.py
src/docs/library/base_ui/components/base/typography.py
src/docs/library/base_ui/icons/hugeicon.py
sapphireui-0.4.4.dist-info/METADATA
sapphireui-0.4.4.dist-info/WHEEL
sapphireui-0.4.4.dist-info/entry_points.txt
sapphireui-0.4.4.dist-info/top_level.txt
sapphireui-0.4.4.dist-info/RECORD
