Metadata-Version: 2.4
Name: sapphireui
Version: 0.4.4
Summary: SapphireUI – The UI Library for Reflex Developers
Author-email: sapphireUI <sapphireui00@gmail.com>
Project-URL: Homepage, https://github.com/sapphireUI/SapphireUI
Project-URL: Documentation, https://sapphireui-blue-book.reflex.run/docs/getting-started/introduction
Project-URL: Source, https://github.com/sapphireUI/SapphireUI
Project-URL: Issues, https://github.com/sapphireUI/SapphireUI/issues
Requires-Python: >=3.11
License-File: LICENSE
Requires-Dist: reflex>=0.8.17
Requires-Dist: pre-commit>=4.2.0
Requires-Dist: black>=25.1.0
Requires-Dist: typer>=0.12.3
Requires-Dist: sapphireui>=0.3.3b0
Dynamic: license-file
